qsignal/__init__.py
qsignal-1.0.2b1.dist-info/DESCRIPTION.rst
qsignal-1.0.2b1.dist-info/METADATA
qsignal-1.0.2b1.dist-info/RECORD
qsignal-1.0.2b1.dist-info/WHEEL
qsignal-1.0.2b1.dist-info/metadata.json
qsignal-1.0.2b1.dist-info/top_level.txt
