Metadata-Version: 2.0
Name: qsignal
Version: 1.0.2b1
Summary: A QT signal/slot concept for Python with Weakrefs.
Home-page: https://github.com/complynx/qsignal
Author: Complynx
Author-email: complynx@yandex.ru
License: UNKNOWN
Keywords: signal slot qt weakref
Platform: UNKNOWN
Classifier: Development Status :: 4 - Beta
Classifier: Intended Audience :: Developers
Classifier: Topic :: Software Development :: User Interfaces
Classifier: License :: OSI Approved :: MIT License
Classifier: Programming Language :: Python :: 2
Classifier: Programming Language :: Python :: 2.7
Classifier: Programming Language :: Python :: 3
Classifier: Programming Language :: Python :: 3.4
Classifier: Programming Language :: Python :: 3.5
Classifier: Programming Language :: Python :: 3.6
Provides-Extra: dev
Requires-Dist: check-manifest; extra == 'dev'
Provides-Extra: test
Requires-Dist: coverage; extra == 'test'
